{
  "session_metadata": {
    "session_id": "791563e6-681b-422a-92b2-1f649e2f5d8c",
    "created_at": "2025-07-22T15:22:42.133360",
    "last_interaction": "2025-07-25T12:52:42.465458",
    "tka_version": "modern"
  },
  "workbench_state": {
    "selected_beat_index": null,
    "selected_beat_data": null,
    "start_position_data": null
  },
  "graph_editor_state": {
    "visible": false,
    "selected_beat_index": null,
    "selected_arrow": null,
    "height": 300
  },
  "ui_state": {
    "active_tab": "sequence_builder",
    "beat_layout": {},
    "component_visibility": {}
  }
}